flask_theme_adminlte3/__init__.py
flask_theme_adminlte3/__version__.py
flask_theme_adminlte3/app.py
flask_theme_adminlte3/assets.py
flask_theme_adminlte3/config.py
flask_theme_adminlte3/testing.py
flask_theme_adminlte3/menu/__init__.py
flask_theme_adminlte3/menu/datatypes.py
flask_theme_adminlte3/menu/menus.yml
flask_theme_adminlte3/menu/openapi.yml
flask_theme_adminlte3/theme/__init__.py
flask_theme_adminlte3/theme/constants.py
flask_theme_adminlte3/theme/ext.py
flask_theme_adminlte3/theme/filters.py
flask_theme_adminlte3/theme/views.py
flask_theme_adminlte3/theme/static/css/theme.css
flask_theme_adminlte3/theme/static/demo/demo.js
flask_theme_adminlte3/theme/static/demo/demo3_2.js
flask_theme_adminlte3/theme/static/js/theme.js
flask_theme_adminlte3/theme/static/webfonts/fa-regular-400.ttf
flask_theme_adminlte3/theme/static/webfonts/fa-regular-400.woff
flask_theme_adminlte3/theme/static/webfonts/fa-regular-400.woff2
flask_theme_adminlte3/theme/static/webfonts/fa-solid-900.ttf
flask_theme_adminlte3/theme/static/webfonts/fa-solid-900.woff
flask_theme_adminlte3/theme/static/webfonts/fa-solid-900.woff2
flask_theme_adminlte3/theme/templates/admin/adminlte3-full.html
flask_theme_adminlte3/theme/templates/admin/adminlte3.html
flask_theme_adminlte3/theme/templates/dashboard/card_tools.html
flask_theme_adminlte3/theme/templates/dashboard/gateway.html
flask_theme_adminlte3/theme/templates/dashboard/list_pages.html
flask_theme_adminlte3/theme/templates/dashboard/list_roles.html
flask_theme_adminlte3/theme/templates/dashboard/list_templates.html
flask_theme_adminlte3/theme/templates/dashboard/list_users.html
flask_theme_adminlte3/theme/templates/dashboard/refresh_card.html
flask_theme_adminlte3/theme/templates/dashboard/sqla.html
flask_theme_adminlte3/theme/templates/includes/controlbar.html
flask_theme_adminlte3/theme/templates/includes/favicon.html
flask_theme_adminlte3/theme/templates/includes/footer.html
flask_theme_adminlte3/theme/templates/includes/javascript.html
flask_theme_adminlte3-2.4.7.dist-info/METADATA
flask_theme_adminlte3-2.4.7.dist-info/WHEEL
flask_theme_adminlte3-2.4.7.dist-info/top_level.txt
flask_theme_adminlte3-2.4.7.dist-info/RECORD
