Metadata-Version: 2.1
Name: flask-theme-adminlte3
Version: 2.4.7
Summary: UNKNOWN
Home-page: UNKNOWN
License: UNKNOWN
Platform: UNKNOWN
Requires-Dist: flask
Requires-Dist: pyyaml
Provides-Extra: dev
Requires-Dist: wheel ; extra == 'dev'
Requires-Dist: twine ; extra == 'dev'
Requires-Dist: pytest ; extra == 'dev'
Requires-Dist: flask-debugtoolbar ; extra == 'dev'
Requires-Dist: flask-assets ; extra == 'dev'
Requires-Dist: jsmin ; extra == 'dev'
Requires-Dist: cssmin ; extra == 'dev'
Requires-Dist: pre-commit ; extra == 'dev'
Requires-Dist: flask-mkdocs ; extra == 'dev'
